TCR_numba
