Metadata-Version: 1.1
Name: TCR-numba
Version: 0.1.1
Summary: some description
Home-page: https://github.com/Paul44444/capybaras_test
Author: Paul
Author-email: richtepp@physik.hu-berlin.de
License: BSD 2-clause
Platform: UNKNOWN
Classifier: Development Status :: 1 - Planning
Classifier: Intended Audience :: Science/Research
Classifier: License :: OSI Approved :: BSD License
Classifier: Operating System :: POSIX :: Linux
Classifier: Programming Language :: Python :: 2
Classifier: Programming Language :: Python :: 2.7
Classifier: Programming Language :: Python :: 3
Classifier: Programming Language :: Python :: 3.4
Classifier: Programming Language :: Python :: 3.5
